{"readme.md":"2b3d2571","index.md":"5db45344","introduce_index.md":"73bd6d03","notes_algorithm.md":"a843637b","notes_basis.md":"5b35ad42","notes_consume_consume.md":"0d3d9b26","notes_consume_lowcost.md":"cd2eb284","notes_css.md":"c49ecea0","notes_data1.md":"4a52a460","notes_design.md":"d95669dc","notes_douyin_local_life.md":"f499a5e2","notes_douyin_travel.md":"2cd7bc6d","notes_html.md":"252eebd6","notes_interview_code.md":"b5e36bad","notes_interview_css.md":"206c9363","notes_interview_javascript.md":"38a47f21","notes_interview_node.md":"f697b292","notes_interview_performance.md":"5c1b2590","notes_interview_webpack.md":"c9df617d","notes_javascript.md":"95a2c212","notes_kuaishou_account.md":"33b80227","notes_kuaishou_basic.md":"5ca59f7c","notes_kuaishou_card.md":"45bd5b77","notes_kuaishou_guide.md":"91014445","notes_kuaishou_investmentflow.md":"2d9d1680","notes_kuaishou_livebroadcast.md":"924ec935","notes_kuaishou_product.md":"b6f6378e","notes_kuaishou_video.md":"99b215bb","notes_manage_index.md":"cfbc11ae","notes_mode_profit.md":"9f9321bc","notes_mysql.md":"db26d7af","notes_product_stockings.md":"5715c271","notes_react.md":"d36c7804","notes_resetful.md":"f39cd73e","notes_shipinhao_account.md":"3ba92ab6","notes_shipinhao_basic.md":"ddaafbee","notes_typescript.md":"8a5e1345","notes_vim.md":"d95a9cce","notes_vue.md":"d5cc645a","notes_xushijie.md":"54e683e9","notes_yarn.md":"4b73840e","projects_j-http-code.md":"196c0f3a","projects_j-is.md":"0dab3cb5","resources_index.md":"09771071"}
