{"readme.md":"5322c6a3","index.md":"e2ab3b78","introduce_index.md":"9e117807","notes_algorithm.md":"d4a750ce","notes_basis.md":"f7fbfe63","notes_consume_consume.md":"7c798c05","notes_consume_lowcost.md":"a0d3f9e3","notes_css.md":"e381bc9c","notes_data1.md":"1306b802","notes_design.md":"e1b4cc4f","notes_douyin_local_life.md":"e77d3826","notes_douyin_travel.md":"a2d2d14b","notes_html.md":"93882eb3","notes_interview_code.md":"a400e434","notes_interview_css.md":"29e032a6","notes_interview_javascript.md":"4be8e51c","notes_interview_node.md":"03786587","notes_interview_performance.md":"3c9ae2b2","notes_interview_webpack.md":"dbd37eec","notes_javascript.md":"b1190f0e","notes_kuaishou_account.md":"1c6bc1fa","notes_kuaishou_basic.md":"574e4bd0","notes_kuaishou_card.md":"9e9a71dc","notes_kuaishou_guide.md":"b8dd85aa","notes_kuaishou_investmentflow.md":"e9cec454","notes_kuaishou_livebroadcast.md":"22d018d4","notes_kuaishou_product.md":"04d193c4","notes_kuaishou_video.md":"09da393b","notes_mode_profit.md":"be8570eb","notes_mysql.md":"0125eb9e","notes_product_stockings.md":"3839d060","notes_react.md":"b0588bdf","notes_resetful.md":"08ef79ad","notes_shipinhao_account.md":"045e88a7","notes_shipinhao_basic.md":"b53c058a","notes_typescript.md":"d2c87207","notes_vim.md":"17f6410d","notes_vue.md":"1327b4d9","notes_xushijie.md":"4fd80499","notes_yarn.md":"75229344","projects_j-http-code.md":"ce39c352","projects_j-is.md":"1eb03793","resources_index.md":"abcfad41"}
